spyfi/__init__.py
spyfi/py.typed
spyfi-1.0.0a0.dist-info/LICENSE
spyfi-1.0.0a0.dist-info/WHEEL
spyfi-1.0.0a0.dist-info/METADATA
spyfi-1.0.0a0.dist-info/RECORD
