Metadata-Version: 2.1
Name: spyfi
Version: 1.0.0a0
Summary: Spyfi
Home-page: https://github.com/bobthemighty/spyfi
License: MIT
Author: Bob Gregory
Author-email: bob@codefiend.co.uk
Requires-Python: >=3.7,<4.0
Classifier: Development Status :: 3 - Alpha
Classifier: License :: OSI Approved :: MIT License
Classifier: Programming Language :: Python :: 3
Classifier: Programming Language :: Python :: 3.10
Classifier: Programming Language :: Python :: 3.7
Classifier: Programming Language :: Python :: 3.8
Classifier: Programming Language :: Python :: 3.9
Requires-Dist: click (>=8.0.1)
Project-URL: Changelog, https://github.com/bobthemighty/spyfi/releases
Project-URL: Documentation, https://spyfi.readthedocs.io
Project-URL: Repository, https://github.com/bobthemighty/spyfi
